automl/__init__.py
automl/automl.py
automl/automl_utils.py
automl/dltabular_tf.py
automl/aggregation/__init__.py
automl/aggregation/aggregation.py
automl/pipelines/__init__.py
automl/pipelines/pipelines.py
automl_helpers-0.0.2.dist-info/LICENSE
automl_helpers-0.0.2.dist-info/METADATA
automl_helpers-0.0.2.dist-info/WHEEL
automl_helpers-0.0.2.dist-info/top_level.txt
automl_helpers-0.0.2.dist-info/RECORD
