Metadata-Version: 2.1
Name: automl-helpers
Version: 0.0.2
Summary: A small package to help with modeling pipelines
Home-page: https://github.com/markovian99/automl-helpers
Author: Example Author
Author-email: author@example.com
Project-URL: Bug Tracker, https://github.com/markovian99/automl-helpers/issues
Classifier: Programming Language :: Python :: 3
Classifier: License :: OSI Approved :: MIT License
Classifier: Operating System :: OS Independent
Requires-Python: >=3.6
License-File: LICENSE
